starsigndna/__init__.py
starsigndna/bootstrapping.py
starsigndna/cli.py
starsigndna/count_mutation_cli.py
starsigndna/cucumber.py
starsigndna/denovo.py
starsigndna/main_fixed_denovo.py
starsigndna/refit.py
starsigndna-1.0.4.dist-info/AUTHORS.rst
starsigndna-1.0.4.dist-info/LICENSE
starsigndna-1.0.4.dist-info/METADATA
starsigndna-1.0.4.dist-info/WHEEL
starsigndna-1.0.4.dist-info/entry_points.txt
starsigndna-1.0.4.dist-info/top_level.txt
starsigndna-1.0.4.dist-info/RECORD
